optics/__init__.py
optics/base_window.py
optics/init_window.py
optics/load_setup.py
optics/main.py
optics/optics_item.py
optics/work_405_window.py
optics/data/iof.txt
optics/data/iof_gas.txt
optics/work_405/__init__.py
optics/work_405/element_items.py
optics/work_405/setup_405.py
optics/work_405/work_405_window.py
optics/work_407/__init__.py
optics/work_407/electric_field.py
optics/work_407/work_407_physics.py
optics/work_407/work_407_setup.py
optics/work_407/work_407_window.py
optics/work_407/work_407_zero.py
mipt_npm_optics-0.0.2.dev2.dist-info/LICENSE
mipt_npm_optics-0.0.2.dev2.dist-info/METADATA
mipt_npm_optics-0.0.2.dev2.dist-info/WHEEL
mipt_npm_optics-0.0.2.dev2.dist-info/entry_points.txt
mipt_npm_optics-0.0.2.dev2.dist-info/top_level.txt
mipt_npm_optics-0.0.2.dev2.dist-info/RECORD
