Metadata-Version: 2.1
Name: mipt-npm-optics
Version: 0.0.2.dev2
Summary: Python scripts for optics lab
Home-page: http://npm.mipt.ru/
Author: Mikhail Zelenyi
Author-email: mihail.zelenyy@phystech.edu
License: MIT License
Keywords: optics
Platform: UNKNOWN
Classifier: Programming Language :: Python :: 3
Classifier: License :: OSI Approved :: MIT License
Classifier: Operating System :: OS Independent
Requires-Dist: numpy
Requires-Dist: scipy
Requires-Dist: matplotlib
Requires-Dist: pyqt5
Requires-Dist: appdirs
Requires-Dist: diffractio
Requires-Dist: hickle
Requires-Dist: pandas
Requires-Dist: pillow
